[
  {
    "productos": [
      {
        "nombre": "Congelador Horizontal Brandt BFK099EBW, 85 cm, 99 L, Eficiencia E - Blanco",
        "precio": "159 €",
        "disponibilidad": "Congelador Horizontal Brandt BFK099EBW, 85 cm, 99 L, Eficiencia E - Blanco"
      },
      {
        "nombre": "Congelador Vertical Infinition CV-88L8XEH, 84.5 cm, 85 L, 3 Cajones, Eficiencia E - Inoxidable",
        "precio": "No disponible",
        "disponibilidad": "Congelador Vertical Infinition CV-88L8XEH, 84.5 cm, 85 L, 3 Cajones, Eficiencia E - Inoxidable"
      },
      {
        "nombre": "Congelador Horizontal Infiniton CH-20H86WEH, 83,5 cm, 207 L, Eficiencia E - Blanco",
        "precio": "219 €",
        "disponibilidad": "Congelador Horizontal Infiniton CH-20H86WEH, 83,5 cm, 207 L, Eficiencia E - Blanco"
      },
      {
        "nombre": "Congelador Horizontal Frigelux CCO100BE, 85 cm, 100 L, Eficiencia E - Blanco",
        "precio": "No disponible",
        "disponibilidad": "Congelador Horizontal Frigelux CCO100BE, 85 cm, 100 L, Eficiencia E - Blanco"
      },
      {
        "nombre": "Congelador Vertical Infiniton CV-172L14BEM, 143,5 cm, 178 L, 6 Cajones, Eficiencia E - Blanco",
        "precio": "299 €",
        "disponibilidad": "Congelador Vertical Infiniton CV-172L14BEM, 143,5 cm, 178 L, 6 Cajones, Eficiencia E - Blanco"
      },
      {
        "nombre": "Congelador Horizontal Infiniton CH15H86WEH, 85,5 cm, 150 L, Eficiencia E - Blanco",
        "precio": "No disponible",
        "disponibilidad": "Congelador Horizontal Infiniton CH15H86WEH, 85,5 cm, 150 L, Eficiencia E - Blanco"
      },
      {
        "nombre": "Congelador Horizontal Infiniton CH-10H86WEH, 83,5 cm, 104 L, Eficiencia E - Blanco",
        "precio": "179 €",
        "disponibilidad": "Congelador Horizontal Infiniton CH-10H86WEH, 83,5 cm, 104 L, Eficiencia E - Blanco"
      },
      {
        "nombre": "Congelador Horizontal Hisense FT125D4AWE, 85.4 cm, 95 L, Eficiencia E - Blanco",
        "precio": "No disponible",
        "disponibilidad": "Congelador Horizontal Hisense FT125D4AWE, 85.4 cm, 95 L, Eficiencia E - Blanco"
      },
      {
        "nombre": "Congelador Frigelux CANF240BE, No Frost, 172 cm, 240 L, 4 Cajones, Eficiencia E - Blanco",
        "precio": "No disponible",
        "disponibilidad": "Congelador Frigelux CANF240BE, No Frost, 172 cm, 240 L, 4 Cajones, Eficiencia E - Blanco"
      },
      {
        "nombre": "Congelador Vertical Hisense FV191N4AW2, No Frost, 143.4 cm, 155 L, 4 Cajones, Eficiencia E - Blanco",
        "precio": "No disponible",
        "disponibilidad": "Congelador Vertical Hisense FV191N4AW2, No Frost, 143.4 cm, 155 L, 4 Cajones, Eficiencia E - Blanco"
      },
      {
        "nombre": "Congelador Vertical Infiniton E CV-1HE84 - Blanco",
        "precio": "No disponible",
        "disponibilidad": "Congelador Vertical Infiniton E CV-1HE84 - Blanco"
      },
      {
        "nombre": "Congelador Horizontal Brandt BFK143EBW, 85 cm, 142 L, Eficiencia E - Blanco",
        "precio": "189 €",
        "disponibilidad": "Congelador Horizontal Brandt BFK143EBW, 85 cm, 142 L, Eficiencia E - Blanco"
      }
    ],
    "fuente": "playwright",
    "url": "https://www.carrefour.es/electrodomesticos/frigorificos-congeladores/congeladores/cat4164161/c"
  },
  {
    "productos": [
      {
        "nombre": "Congelador Horizontal Hisense FT546D4AWLYE, 85.5 cm, 420 L, Eficiencia E - Blanco",
        "precio": "499 €",
        "disponibilidad": "Congelador Horizontal Hisense FT546D4AWLYE, 85.5 cm, 420 L, Eficiencia E - Blanco"
      },
      {
        "nombre": "Congelador Horizontal Hisense FT247D4AWYLE, 85.3 cm, 191 L, Eficiencia E - Blanco",
        "precio": "No disponible",
        "disponibilidad": "Congelador Horizontal Hisense FT247D4AWYLE, 85.3 cm, 191 L, Eficiencia E - Blanco"
      },
      {
        "nombre": "Congelador Vertical Balay 3GFE563WE, No Frost, 186 cm, 242 L, 4 Cajones, Eficiencia E - Blanco",
        "precio": "No disponible",
        "disponibilidad": "Congelador Vertical Balay 3GFE563WE, No Frost, 186 cm, 242 L, 4 Cajones, Eficiencia E - Blanco"
      },
      {
        "nombre": "Congelador Horizontal Frigelux CCO400BE, 84,5 cm, 395 L, Eficiencia E - Blanco",
        "precio": "No disponible",
        "disponibilidad": "Congelador Horizontal Frigelux CCO400BE, 84,5 cm, 395 L, Eficiencia E - Blanco"
      },
      {
        "nombre": "Congelador Horizontal Candy CCHH 145E, 84,5 cm, 137 L, Eficiencia E - Blanco",
        "precio": "229 €",
        "disponibilidad": "Congelador Horizontal Candy CCHH 145E, 84,5 cm, 137 L, Eficiencia E - Blanco"
      },
      {
        "nombre": "Congelador Horizontal 93l Display En Puerta Blanco Schneider Sccfd93w+",
        "precio": "179,90 €",
        "disponibilidad": "Congelador Horizontal 93l Display En Puerta Blanco Schneider Sccfd93w+"
      },
      {
        "nombre": "Congelador Vertical Icecool ICFZ145EW, 145,5 cm, 188 L, Eficiencia E - Blanco",
        "precio": "No disponible",
        "disponibilidad": "Congelador Vertical Icecool ICFZ145EW, 145,5 cm, 188 L, Eficiencia E - Blanco"
      },
      {
        "nombre": "Congelador Horizontal Candy CCHH 200E, No Frost, 84,5 cm, 197 L, Eficiencia E - Blanco",
        "precio": "259 €",
        "disponibilidad": "Congelador Horizontal Candy CCHH 200E, No Frost, 84,5 cm, 197 L, Eficiencia E - Blanco"
      },
      {
        "nombre": "Congelador Vertical Infinition CV-140L25WEP, 125.9 cm, 145 L, 5 Cajones, Eficiencia E - Blanco",
        "precio": "No disponible",
        "disponibilidad": "Congelador Vertical Infinition CV-140L25WEP, 125.9 cm, 145 L, 5 Cajones, Eficiencia E - Blanco"
      },
      {
        "nombre": "Congelador Horizontal Hisense FT184D4AWYE, 85.4 cm, 142 L, Eficiencia E - Blanco",
        "precio": "No disponible",
        "disponibilidad": "Congelador Horizontal Hisense FT184D4AWYE, 85.4 cm, 142 L, Eficiencia E - Blanco"
      },
      {
        "nombre": "Congelador Vertical Frigelux E CV71",
        "precio": "No disponible",
        "disponibilidad": "Congelador Vertical Frigelux E CV71"
      },
      {
        "nombre": "Congelador Horizontal Frigelux CCO300BE, 84 cm, 290 L, Eficiencia E - Blanco",
        "precio": "No disponible",
        "disponibilidad": "Congelador Horizontal Frigelux CCO300BE, 84 cm, 290 L, Eficiencia E - Blanco"
      },
      {
        "nombre": "Congelador Vertical NEW POL NWFZ1861, No Frost, 186 cm, 278 L, Eficiencia E - Inoxidable",
        "precio": "No disponible",
        "disponibilidad": "Congelador Vertical NEW POL NWFZ1861, No Frost, 186 cm, 278 L, Eficiencia E - Inoxidable"
      },
      {
        "nombre": "Congelador Horizontal Vok Evf-99cdew, 55cm, 99 L, Función Dual, Blanco, Luz Led, Eficiencia E",
        "precio": "149 €",
        "disponibilidad": "Congelador Horizontal Vok Evf-99cdew, 55cm, 99 L, Función Dual, Blanco, Luz Led, Eficiencia E"
      },
      {
        "nombre": "Congelador Vertical Cv-125b Infiniton (E, Blanco, Ciclico, Altura 125cm) Instalacion Incluida",
        "precio": "299 €",
        "disponibilidad": "Congelador Vertical Cv-125b Infiniton (E, Blanco, Ciclico, Altura 125cm) Instalacion Incluida"
      },
      {
        "nombre": "Congelador Horizontal Brandt BFK381ESW, 85 cm, 382 L, Eficiencia E - Blanco",
        "precio": "449 €",
        "disponibilidad": "Congelador Horizontal Brandt BFK381ESW, 85 cm, 382 L, Eficiencia E - Blanco"
      },
      {
        "nombre": "Congelador Horizontal Brandt BFK301ESW, 85 cm, 315 L, Eficiencia E - Blanco",
        "precio": "400,09 €",
        "disponibilidad": "Congelador Horizontal Brandt BFK301ESW, 85 cm, 315 L, Eficiencia E - Blanco"
      },
      {
        "nombre": "Congelador Vertical Chiq | 166 Litros | No Frost | Color Negro Inox - Fsd166ne4e",
        "precio": "399,99 €",
        "disponibilidad": "Congelador Vertical Chiq | 166 Litros | No Frost | Color Negro Inox - Fsd166ne4e"
      },
      {
        "nombre": "Congelador Horizontal Con Puertas De Cristal Corredoras 265l Jocel",
        "precio": "No disponible",
        "disponibilidad": "Congelador Horizontal Con Puertas De Cristal Corredoras 265l Jocel"
      },
      {
        "nombre": "Congelador Vertical Cv-128x Infiniton (E, Inox, Ciclico, Altura 125cm) Instalacion Incluida",
        "precio": "319 €",
        "disponibilidad": "Congelador Vertical Cv-128x Infiniton (E, Inox, Ciclico, Altura 125cm) Instalacion Incluida"
      },
      {
        "nombre": "Congelador Horizontal Brandt BFK151ESW, 84,5 cm, 150 L, Eficiencia E - Blanco",
        "precio": "274,79 €",
        "disponibilidad": "Congelador Horizontal Brandt BFK151ESW, 84,5 cm, 150 L, Eficiencia E - Blanco"
      },
      {
        "nombre": "Infiniton Ch-a98b - Congelador Horizontal, Blanco, 98 Litros, Control Temperatura Mecánico, Dualsystem, Fast Freeze, Incluye Cesto",
        "precio": "159 €",
        "disponibilidad": "Infiniton Ch-a98b - Congelador Horizontal, Blanco, 98 Litros, Control Temperatura Mecánico, Dualsystem, Fast Freeze, Incluye Cesto"
      },
      {
        "nombre": "Congelador Vertical Infiniton Cv-a174b, 240 L, 172 Cm, E, Total No Frost, Blanco",
        "precio": "469 €",
        "disponibilidad": "Congelador Vertical Infiniton Cv-a174b, 240 L, 172 Cm, E, Total No Frost, Blanco"
      },
      {
        "nombre": "Congelador Vertical LG GFT41PZGSZ, No Frost, 186 cm, 324 L, Eficiencia E - Inoxidable",
        "precio": "No disponible",
        "disponibilidad": "Congelador Vertical LG GFT41PZGSZ, No Frost, 186 cm, 324 L, Eficiencia E - Inoxidable"
      }
    ],
    "fuente": "playwright",
    "url": "https://www.carrefour.es/electrodomesticos/frigorificos-congeladores/congeladores/cat4164161/c?offset=24"
  },
  {
    "productos": [
      {
        "nombre": "Congelador Horizontal Brandt BFK201ESW, 84,5 cm, 198 L, Eficiencia E - Blanco",
        "precio": "315,95 €",
        "disponibilidad": "Congelador Horizontal Brandt BFK201ESW, 84,5 cm, 198 L, Eficiencia E - Blanco"
      },
      {
        "nombre": "Cecotec Congelador Vertical Bolero Coolmarket Tf 97 Black",
        "precio": "239 €",
        "disponibilidad": "Cecotec Congelador Vertical Bolero Coolmarket Tf 97 Black"
      },
      {
        "nombre": "Congelador Arcón Blanco 2 En 1 De 142l | Universalblue",
        "precio": "189,99 €",
        "disponibilidad": "Congelador Arcón Blanco 2 En 1 De 142l | Universalblue"
      },
      {
        "nombre": "Congelador Vertical Chiq 145l | 5 Cajones | Puerta Reversible | Chiq",
        "precio": "289,99 €",
        "disponibilidad": "Congelador Vertical Chiq 145l | 5 Cajones | Puerta Reversible | Chiq"
      },
      {
        "nombre": "Milectric Congelador Arcon Arc-n01-99 Litros, A+/f, Función Fast Freeze, Dual System, Control De Temperatura",
        "precio": "169 €",
        "disponibilidad": "Milectric Congelador Arcon Arc-n01-99 Litros, A+/f, Función Fast Freeze, Dual System, Control De Temperatura"
      },
      {
        "nombre": "Congelador Horizontal Vok Evf-137cdew, 63cm, 137 L, Función Dual, Blanco, Luz Led, Eficiencia E",
        "precio": "169 €",
        "disponibilidad": "Congelador Horizontal Vok Evf-137cdew, 63cm, 137 L, Función Dual, Blanco, Luz Led, Eficiencia E"
      },
      {
        "nombre": "Congelador Vertical Elecsan , Dimensión 142cm X 54,5cm X 56cm, Capacidad 176-156litros, Color Inoxidable , Bajo Consumo A++/ E",
        "precio": "319 €",
        "disponibilidad": "Congelador Vertical Elecsan , Dimensión 142cm X 54,5cm X 56cm, Capacidad 176-156litros, Color Inoxidable , Bajo Consumo A++/ E"
      },
      {
        "nombre": "Congelador Vertical Chiq 85l | 3 Cajones | Puerta Reversible | Chiq",
        "precio": "199,99 €",
        "disponibilidad": "Congelador Vertical Chiq 85l | 3 Cajones | Puerta Reversible | Chiq"
      }
    ],
    "fuente": "playwright",
    "url": "https://www.carrefour.es/electrodomesticos/frigorificos-congeladores/congeladores/cat4164161/c?offset=48"
  },
  {
    "productos": [
      {
        "nombre": "Congelador Vertical Integrable AEG F ABE818F6NS",
        "precio": "No disponible",
        "disponibilidad": "Congelador Vertical Integrable AEG F ABE818F6NS"
      },
      {
        "nombre": "Candy Artico Chae 2002e Arcón Congelador Independiente 196 L E Blanco",
        "precio": "No disponible",
        "disponibilidad": "Candy Artico Chae 2002e Arcón Congelador Independiente 196 L E Blanco"
      },
      {
        "nombre": "Arcón Congelador Infiniton Ch-mf50 500l Defrost 4d Cooling E Blanco 165 Cm",
        "precio": "No disponible",
        "disponibilidad": "Arcón Congelador Infiniton Ch-mf50 500l Defrost 4d Cooling E Blanco 165 Cm"
      },
      {
        "nombre": "Infiniton Congelador Vertical Cv-265l85peh, 282 L, 185 Cm, No Frost, Inverter, E, Stone Outlook",
        "precio": "No disponible",
        "disponibilidad": "Infiniton Congelador Vertical Cv-265l85peh, 282 L, 185 Cm, No Frost, Inverter, E, Stone Outlook"
      },
      {
        "nombre": "Infiniton Cv-a52b - Congelador Vertical Mini, Blanco, 33 Litros, Control De Temperatura Mecánico, Puerta Reversible, Clase A+/e",
        "precio": "139 €",
        "disponibilidad": "Infiniton Cv-a52b - Congelador Vertical Mini, Blanco, 33 Litros, Control De Temperatura Mecánico, Puerta Reversible, Clase A+/e"
      },
      {
        "nombre": "Infiniton Cv-a142b - Congelador Vertical, Blanco, 172 Litros, Alto 144cm, Tecnologia Defrost, Cíclico, Clase A+/f",
        "precio": "349 €",
        "disponibilidad": "Infiniton Cv-a142b - Congelador Vertical, Blanco, 172 Litros, Alto 144cm, Tecnologia Defrost, Cíclico, Clase A+/f"
      },
      {
        "nombre": "Congelador Vertical Infiniton E CV125B",
        "precio": "No disponible",
        "disponibilidad": "Congelador Vertical Infiniton E CV125B"
      },
      {
        "nombre": "Congelador Horizontal Congelador Bolero Coolmarket Chest 99 White E, 99 L, Clase E, Dual Fuction: Congelador Y Frigorífico, Control Mecánico",
        "precio": "211,99 €",
        "disponibilidad": "Congelador Horizontal Congelador Bolero Coolmarket Chest 99 White E, 99 L, Clase E, Dual Fuction: Congelador Y Frigorífico, Control Mecánico"
      }
    ],
    "fuente": "playwright",
    "url": "https://www.carrefour.es/electrodomesticos/frigorificos-congeladores/congeladores/cat4164161/c?offset=72"
  },
  {
    "productos": [
      {
        "nombre": "Congelador Balay 3gfe568xe Inox 1.86m E",
        "precio": "No disponible",
        "disponibilidad": "Congelador Balay 3gfe568xe Inox 1.86m E"
      },
      {
        "nombre": "Congelador Horizontal 142l Jocel",
        "precio": "No disponible",
        "disponibilidad": "Congelador Horizontal 142l Jocel"
      },
      {
        "nombre": "Congelador Arcón Hisense Ft321d4awle 0.96m 250l E",
        "precio": "327,36 €",
        "disponibilidad": "Congelador Arcón Hisense Ft321d4awle 0.96m 250l E"
      },
      {
        "nombre": "Congelador Arcón Hisense Ft386d4awlye 1.11m 300l E",
        "precio": "361,99 €",
        "disponibilidad": "Congelador Arcón Hisense Ft386d4awlye 1.11m 300l E"
      },
      {
        "nombre": "Congelador Zanussi Zcan38fw1",
        "precio": "No disponible",
        "disponibilidad": "Congelador Zanussi Zcan38fw1"
      },
      {
        "nombre": "Congelador Horizontal Candy F CCHH 100",
        "precio": "227,79 €",
        "disponibilidad": "Congelador Horizontal Candy F CCHH 100"
      },
      {
        "nombre": "Cecotec Mini Frigorífico Bolero Coolmarket Tt 31 Dual Black E",
        "precio": "No disponible",
        "disponibilidad": "Cecotec Mini Frigorífico Bolero Coolmarket Tt 31 Dual Black E"
      },
      {
        "nombre": "Cecotec Congelador Horizontal Bolero Coolmarket Chest 254 White E",
        "precio": "No disponible",
        "disponibilidad": "Cecotec Congelador Horizontal Bolero Coolmarket Chest 254 White E"
      }
    ],
    "fuente": "playwright",
    "url": "https://www.carrefour.es/electrodomesticos/frigorificos-congeladores/congeladores/cat4164161/c?offset=96"
  },
  {
    "productos": [
      {
        "nombre": "Arcón Congelador Kunft Kcf9121 130w 198l Estático E Blanco 85 Cm",
        "precio": "234,99 €",
        "disponibilidad": "Arcón Congelador Kunft Kcf9121 130w 198l Estático E Blanco 85 Cm"
      },
      {
        "nombre": "Arcón Congelador Kunft Kcf9120 100l Horizontal F Blanco 54,5 Cm",
        "precio": "204,97 €",
        "disponibilidad": "Arcón Congelador Kunft Kcf9120 100l Horizontal F Blanco 54,5 Cm"
      },
      {
        "nombre": "Congelador Vertical No Frost, Hotpoint F UH8 F1C X 1",
        "precio": "720,99 €",
        "disponibilidad": "Congelador Vertical No Frost, Hotpoint F UH8 F1C X 1"
      },
      {
        "nombre": "Haier Hce420e Arcón Congelador Independiente 418 L E Blanco",
        "precio": "No disponible",
        "disponibilidad": "Haier Hce420e Arcón Congelador Independiente 418 L E Blanco"
      },
      {
        "nombre": "Haier Hce100e/ Arcón Congelador Independiente 97 L E Blanco",
        "precio": "229,60 €",
        "disponibilidad": "Haier Hce100e/ Arcón Congelador Independiente 97 L E Blanco"
      },
      {
        "nombre": "Candy Chae 1002e Arcón Congelador Independiente 97 L E Blanco",
        "precio": "195,99 €",
        "disponibilidad": "Candy Chae 1002e Arcón Congelador Independiente 97 L E Blanco"
      },
      {
        "nombre": "Arcón Congelador Cecotec Bolero Coolmarket Chest 142 White E 142l Dual Function E Blanco 83,5 Cm",
        "precio": "220,90 €",
        "disponibilidad": "Arcón Congelador Cecotec Bolero Coolmarket Chest 142 White E 142l Dual Function E Blanco 83,5 Cm"
      },
      {
        "nombre": "Infiniton Cv-14n38 - Congelador Vertical, Inox, 172 Litros, Cíclico, Tecnología Defrost, 6 Cajones",
        "precio": "No disponible",
        "disponibilidad": "Infiniton Cv-14n38 - Congelador Vertical, Inox, 172 Litros, Cíclico, Tecnología Defrost, 6 Cajones"
      },
      {
        "nombre": "Congelador Vertical Infiniton Cv-184l14web, 155 L, 143.4 Cm, Total No Frost, E, Blanco",
        "precio": "No disponible",
        "disponibilidad": "Congelador Vertical Infiniton Cv-184l14web, 155 L, 143.4 Cm, Total No Frost, E, Blanco"
      },
      {
        "nombre": "Congelador Vertical Infiniton Cv-265l85wem, 282 Litros, 185 Cm, No Frost, E, Fabricador De Hielo Manual Incorporado, Blanco",
        "precio": "No disponible",
        "disponibilidad": "Congelador Vertical Infiniton Cv-265l85wem, 282 Litros, 185 Cm, No Frost, E, Fabricador De Hielo Manual Incorporado, Blanco"
      },
      {
        "nombre": "Congelador Vertical Svan Scv185600enfx No Frost 274l E Inox 185,5 Cm",
        "precio": "599,99 €",
        "disponibilidad": "Congelador Vertical Svan Scv185600enfx No Frost 274l E Inox 185,5 Cm"
      },
      {
        "nombre": "Congelador Vertical Svan Scv185600enf No Frost 274l E Blanco 185,5 Cm",
        "precio": "574 €",
        "disponibilidad": "Congelador Vertical Svan Scv185600enf No Frost 274l E Blanco 185,5 Cm"
      },
      {
        "nombre": "Congelador Arcón Beko Hsm46740 1.55m 451l E",
        "precio": "588,19 €",
        "disponibilidad": "Congelador Arcón Beko Hsm46740 1.55m 451l E"
      },
      {
        "nombre": "Congelador Integrable Beko Bu1204n 0.82m E",
        "precio": "No disponible",
        "disponibilidad": "Congelador Integrable Beko Bu1204n 0.82m E"
      },
      {
        "nombre": "Congelador Integrable Beko Bfna247e40sn 1.77m E",
        "precio": "634,98 €",
        "disponibilidad": "Congelador Integrable Beko Bfna247e40sn 1.77m E"
      },
      {
        "nombre": "Lg Congelador Vertical 60cm 324l Nofrost - Gft61swcse",
        "precio": "No disponible",
        "disponibilidad": "Lg Congelador Vertical 60cm 324l Nofrost - Gft61swcse"
      },
      {
        "nombre": "Congelador Vertical Samsung Rz32c7bb6s9ef 323l",
        "precio": "1.177,81 €",
        "disponibilidad": "Congelador Vertical Samsung Rz32c7bb6s9ef 323l"
      },
      {
        "nombre": "Congelador Vertical Samsung Rz32c7cbeb1ef 323l",
        "precio": "No disponible",
        "disponibilidad": "Congelador Vertical Samsung Rz32c7cbeb1ef 323l"
      },
      {
        "nombre": "Infiniton Ch-a142b - Congelador Horizontal, Blanco, 142 Litros, Control Temperatura Mecánico, Dualsystem, Fast Freeze, Incluye Cesto Y Ruedas",
        "precio": "209 €",
        "disponibilidad": "Infiniton Ch-a142b - Congelador Horizontal, Blanco, 142 Litros, Control Temperatura Mecánico, Dualsystem, Fast Freeze, Incluye Cesto Y Ruedas"
      },
      {
        "nombre": "Infiniton Ch-a198b - Congelador Horizontal, Blanco, 198 Litros, Control Temperatura Mecánico, Dualsystem, Fast Freeze, Incluye Cesto Y Ruedas",
        "precio": "249 €",
        "disponibilidad": "Infiniton Ch-a198b - Congelador Horizontal, Blanco, 198 Litros, Control Temperatura Mecánico, Dualsystem, Fast Freeze, Incluye Cesto Y Ruedas"
      },
      {
        "nombre": "California Congelador De Sobremesa 55cm 98l Blanco - Ccfs98aw-11",
        "precio": "No disponible",
        "disponibilidad": "California Congelador De Sobremesa 55cm 98l Blanco - Ccfs98aw-11"
      },
      {
        "nombre": "Congelador Vertical Liebherr E SFNSFE5227",
        "precio": "No disponible",
        "disponibilidad": "Congelador Vertical Liebherr E SFNSFE5227"
      },
      {
        "nombre": "Congelador Horizontal Indesit F OS 1A 100 2",
        "precio": "315,80 €",
        "disponibilidad": "Congelador Horizontal Indesit F OS 1A 100 2"
      },
      {
        "nombre": "Fagor Congelador Vertical 55cm 186l Nofrost - Fafn6192",
        "precio": "No disponible",
        "disponibilidad": "Fagor Congelador Vertical 55cm 186l Nofrost - Fafn6192"
      }
    ],
    "fuente": "playwright",
    "url": "https://www.carrefour.es/electrodomesticos/frigorificos-congeladores/congeladores/cat4164161/c?offset=120"
  },
  {
    "productos": [
      {
        "nombre": "Congelador Vertical NEW POL NWFZ1861I, No Frost, 186 cm, 278 L, Eficiencia E - Inoxidable",
        "precio": "No disponible",
        "disponibilidad": "Congelador Vertical NEW POL NWFZ1861I, No Frost, 186 cm, 278 L, Eficiencia E - Inoxidable"
      },
      {
        "nombre": "Congelador Liebherr G 1223 Comfort Clase F",
        "precio": "No disponible",
        "disponibilidad": "Congelador Liebherr G 1223 Comfort Clase F"
      },
      {
        "nombre": "Congelador Siemens Gs36naxep",
        "precio": "1.113,56 €",
        "disponibilidad": "Congelador Siemens Gs36naxep"
      },
      {
        "nombre": "Congelador Integrable Bosch Giv11afe0 71.2cm A++",
        "precio": "554,08 €",
        "disponibilidad": "Congelador Integrable Bosch Giv11afe0 71.2cm A++"
      },
      {
        "nombre": "Congelador Bosch Gsn36aiep",
        "precio": "1.040,91 €",
        "disponibilidad": "Congelador Bosch Gsn36aiep"
      },
      {
        "nombre": "Congelador Integrable Bosch 177.2x55.8cm Gin81aef0",
        "precio": "No disponible",
        "disponibilidad": "Congelador Integrable Bosch 177.2x55.8cm Gin81aef0"
      },
      {
        "nombre": "Congelador Bosch Gsn36vifp 186cm Inox",
        "precio": "937,11 €",
        "disponibilidad": "Congelador Bosch Gsn36vifp 186cm Inox"
      },
      {
        "nombre": "Congelador Bosch Gsn36awep",
        "precio": "800,52 €",
        "disponibilidad": "Congelador Bosch Gsn36awep"
      },
      {
        "nombre": "Congelador Bosch Gsn33vwep 176cm",
        "precio": "728,71 €",
        "disponibilidad": "Congelador Bosch Gsn33vwep 176cm"
      },
      {
        "nombre": "Congelador Bosch Gsn33vlep 176cm Inox",
        "precio": "845,71 €",
        "disponibilidad": "Congelador Bosch Gsn33vlep 176cm Inox"
      },
      {
        "nombre": "Congelador Integrable Balay 3gif737f No Frost 1772mm",
        "precio": "No disponible",
        "disponibilidad": "Congelador Integrable Balay 3gif737f No Frost 1772mm"
      },
      {
        "nombre": "Congelador Horizontal Midea MDRC152SLF01G",
        "precio": "189 €",
        "disponibilidad": "Congelador Horizontal Midea MDRC152SLF01G"
      },
      {
        "nombre": "Congelador Infiniton CV-51N - Negro",
        "precio": "No disponible",
        "disponibilidad": "Congelador Infiniton CV-51N - Negro"
      },
      {
        "nombre": "Mini Congelador Vertical 91l Jocel",
        "precio": "No disponible",
        "disponibilidad": "Mini Congelador Vertical 91l Jocel"
      },
      {
        "nombre": "Congelador Horizontal Con Tapa De Cristal 93l Jocel",
        "precio": "No disponible",
        "disponibilidad": "Congelador Horizontal Con Tapa De Cristal 93l Jocel"
      },
      {
        "nombre": "Congelador Vertical Jocel De 185cm Y 380l",
        "precio": "No disponible",
        "disponibilidad": "Congelador Vertical Jocel De 185cm Y 380l"
      },
      {
        "nombre": "Congelador Vertical Inox, 185cm 282l Clase E, Jocel",
        "precio": "No disponible",
        "disponibilidad": "Congelador Vertical Inox, 185cm 282l Clase E, Jocel"
      },
      {
        "nombre": "Congelador Vertical Inox, 143cm 172l Jocel",
        "precio": "No disponible",
        "disponibilidad": "Congelador Vertical Inox, 143cm 172l Jocel"
      },
      {
        "nombre": "Congelador Horizontal Jocel / 371l / Cerradura / Clase E",
        "precio": "No disponible",
        "disponibilidad": "Congelador Horizontal Jocel / 371l / Cerradura / Clase E"
      },
      {
        "nombre": "Congelador Horizontal Jocel / 198l / Cerradura / Clase E",
        "precio": "No disponible",
        "disponibilidad": "Congelador Horizontal Jocel / 198l / Cerradura / Clase E"
      },
      {
        "nombre": "Congelador Horizontal Jocel / 142l / Cerradura / Clase E",
        "precio": "No disponible",
        "disponibilidad": "Congelador Horizontal Jocel / 142l / Cerradura / Clase E"
      },
      {
        "nombre": "Congelador Vertical Infiniton E CV-50W",
        "precio": "No disponible",
        "disponibilidad": "Congelador Vertical Infiniton E CV-50W"
      },
      {
        "nombre": "Congelador Vertical Infiniton E CV88",
        "precio": "No disponible",
        "disponibilidad": "Congelador Vertical Infiniton E CV88"
      },
      {
        "nombre": "Congelador Vertical Infiniton E CV-88IX",
        "precio": "No disponible",
        "disponibilidad": "Congelador Vertical Infiniton E CV-88IX"
      }
    ],
    "fuente": "playwright",
    "url": "https://www.carrefour.es/electrodomesticos/frigorificos-congeladores/congeladores/cat4164161/c?offset=144"
  },
  {
    "productos": [
      {
        "nombre": "Congelador Vertical Infiniton E CV19DST",
        "precio": "No disponible",
        "disponibilidad": "Congelador Vertical Infiniton E CV19DST"
      },
      {
        "nombre": "Congelador Whirlpool Uw8 F2y Xbi F 2",
        "precio": "714,61 €",
        "disponibilidad": "Congelador Whirlpool Uw8 F2y Xbi F 2"
      },
      {
        "nombre": "Congelador Whirlpool Uw6 F2y Wbi F 2 Blanco 1.67m",
        "precio": "578,52 €",
        "disponibilidad": "Congelador Whirlpool Uw6 F2y Wbi F 2 Blanco 1.67m"
      },
      {
        "nombre": "Congelador Whirlpool Uw8 F2y Wbi F 2 Blanco 1.87m",
        "precio": "646,99 €",
        "disponibilidad": "Congelador Whirlpool Uw8 F2y Wbi F 2 Blanco 1.87m"
      },
      {
        "nombre": "Congelador Vertical Indesit Ui8f2cw",
        "precio": "553,88 €",
        "disponibilidad": "Congelador Vertical Indesit Ui8f2cw"
      },
      {
        "nombre": "Congelador Horizontal Rommer Ch153 140l",
        "precio": "No disponible",
        "disponibilidad": "Congelador Horizontal Rommer Ch153 140l"
      },
      {
        "nombre": "Congelador Teka Rsf 10080 Blanco 0.85m E",
        "precio": "No disponible",
        "disponibilidad": "Congelador Teka Rsf 10080 Blanco 0.85m E"
      },
      {
        "nombre": "Cecotec Bolero Coolmarket Tf 90 E",
        "precio": "224,90 €",
        "disponibilidad": "Cecotec Bolero Coolmarket Tf 90 E"
      },
      {
        "nombre": "Cecotec Congelador Vertical Bolero Coolmarket Tf 87 Inox",
        "precio": "239,90 €",
        "disponibilidad": "Cecotec Congelador Vertical Bolero Coolmarket Tf 87 Inox"
      },
      {
        "nombre": "Cecotec Congelador Vertical Bolero Coolmarket Tf 87 Black",
        "precio": "No disponible",
        "disponibilidad": "Cecotec Congelador Vertical Bolero Coolmarket Tf 87 Black"
      },
      {
        "nombre": "Congelador Horizontal Bolero Coolmarket Chest 199 White E, Capacidad 199 L, Modo Inverter Plus, Dual Fuction, Fast Freezing, Cesta Interior, Control Electrónico, Clase E",
        "precio": "No disponible",
        "disponibilidad": "Congelador Horizontal Bolero Coolmarket Chest 199 White E, Capacidad 199 L, Modo Inverter Plus, Dual Fuction, Fast Freezing, Cesta Interior, Control Electrónico, Clase E"
      },
      {
        "nombre": "Congelador Arcón Blanco 2 En 1 De 142l | Universalblue",
        "precio": "189,99 €",
        "disponibilidad": "Congelador Arcón Blanco 2 En 1 De 142l | Universalblue"
      },
      {
        "nombre": "Congelador Vertical Cv50 Blanco 40l Solthermic",
        "precio": "No disponible",
        "disponibilidad": "Congelador Vertical Cv50 Blanco 40l Solthermic"
      },
      {
        "nombre": "Congelador Vertical Cv141 Blanco 156l Solthermic",
        "precio": "No disponible",
        "disponibilidad": "Congelador Vertical Cv141 Blanco 156l Solthermic"
      },
      {
        "nombre": "Congelador Vertical Cv141s Inox 156l Solthermic",
        "precio": "No disponible",
        "disponibilidad": "Congelador Vertical Cv141s Inox 156l Solthermic"
      },
      {
        "nombre": "Milectric Congelador Arcon Arc-n02-199 Litros, A+/f, Función Fast Freeze, Dual System, Control De Temperatura",
        "precio": "No disponible",
        "disponibilidad": "Milectric Congelador Arcon Arc-n02-199 Litros, A+/f, Función Fast Freeze, Dual System, Control De Temperatura"
      },
      {
        "nombre": "Congelador Aspes Acv185600enfx Inox1.85m E",
        "precio": "679,99 €",
        "disponibilidad": "Congelador Aspes Acv185600enfx Inox1.85m E"
      },
      {
        "nombre": "Congelador Svan Scvh2600 Cristal 2.05m C",
        "precio": "1.284,64 €",
        "disponibilidad": "Congelador Svan Scvh2600 Cristal 2.05m C"
      },
      {
        "nombre": "Congelador Bajo Encimera Elecsan , Dimensión 54,5cm X 84cm X 56cm, Capacidad 96-80l, Blanco , Bajo Consumo A++/ E",
        "precio": "229 €",
        "disponibilidad": "Congelador Bajo Encimera Elecsan , Dimensión 54,5cm X 84cm X 56cm, Capacidad 96-80l, Blanco , Bajo Consumo A++/ E"
      },
      {
        "nombre": "Congelador Bajo Encimera Elecsan , Dimensión 54,5cm X 84cm X 56cm, Capacidad 96-80l, Color Inox , Bajo Consumo A++/ E",
        "precio": "215 €",
        "disponibilidad": "Congelador Bajo Encimera Elecsan , Dimensión 54,5cm X 84cm X 56cm, Capacidad 96-80l, Color Inox , Bajo Consumo A++/ E"
      },
      {
        "nombre": "Congelador Beko Fs166020",
        "precio": "239,09 €",
        "disponibilidad": "Congelador Beko Fs166020"
      },
      {
        "nombre": "Congelador Arcón Beko Cf100ewn 0.55m 100l E",
        "precio": "No disponible",
        "disponibilidad": "Congelador Arcón Beko Cf100ewn 0.55m 100l E"
      },
      {
        "nombre": "Infiniton Ch-a291b - Congelador Horizontal, Blanco, 291 Litros, Control Temperatura Mecánico, Dualsystem, Fast Freeze, Incluye Cesto Y Ruedas",
        "precio": "359 €",
        "disponibilidad": "Infiniton Ch-a291b - Congelador Horizontal, Blanco, 291 Litros, Control Temperatura Mecánico, Dualsystem, Fast Freeze, Incluye Cesto Y Ruedas"
      },
      {
        "nombre": "Congelador Horizontal 485l Con Cerradura Con Llaves, Jocel",
        "precio": "No disponible",
        "disponibilidad": "Congelador Horizontal 485l Con Cerradura Con Llaves, Jocel"
      }
    ],
    "fuente": "playwright",
    "url": "https://www.carrefour.es/electrodomesticos/frigorificos-congeladores/congeladores/cat4164161/c?offset=168"
  },
  {
    "productos": [
      {
        "nombre": "Congelador Vertical Jocel, 85cm Y 98l, Blanco",
        "precio": "No disponible",
        "disponibilidad": "Congelador Vertical Jocel, 85cm Y 98l, Blanco"
      },
      {
        "nombre": "Congelador Vertical Jocel, 50cm Y 32l, Blanco",
        "precio": "No disponible",
        "disponibilidad": "Congelador Vertical Jocel, 50cm Y 32l, Blanco"
      },
      {
        "nombre": "Haier Hce520e Arcón Congelador Independiente 508 L E Blanco",
        "precio": "No disponible",
        "disponibilidad": "Haier Hce520e Arcón Congelador Independiente 508 L E Blanco"
      },
      {
        "nombre": "Midea Mdrc152fee01 Congelador Horizontal",
        "precio": "179 €",
        "disponibilidad": "Midea Mdrc152fee01 Congelador Horizontal"
      },
      {
        "nombre": "Midea Mdrc564fee01 Congelador Horizontal",
        "precio": "527,31 €",
        "disponibilidad": "Midea Mdrc564fee01 Congelador Horizontal"
      },
      {
        "nombre": "Midea Mdrc207fee01 Congelador Horizontal",
        "precio": "253,64 €",
        "disponibilidad": "Midea Mdrc207fee01 Congelador Horizontal"
      },
      {
        "nombre": "Congelador Vertical Liebherr GP 1213",
        "precio": "No disponible",
        "disponibilidad": "Congelador Vertical Liebherr GP 1213"
      },
      {
        "nombre": "Congelador Horizontal Indesit Os1a-300-h2 311l 2cestos 91,6x118x69,8 A F",
        "precio": "516,45 €",
        "disponibilidad": "Congelador Horizontal Indesit Os1a-300-h2 311l 2cestos 91,6x118x69,8 A F"
      }
    ],
    "fuente": "playwright",
    "url": "https://www.carrefour.es/electrodomesticos/frigorificos-congeladores/congeladores/cat4164161/c?offset=192"
  },
  {
    "productos": [
      {
        "nombre": "Congelador Horizontal 98l Jocel",
        "precio": "No disponible",
        "disponibilidad": "Congelador Horizontal 98l Jocel"
      },
      {
        "nombre": "Congelador Tensai Tcheu500duof Blanco (170 X 86 Cm)",
        "precio": "No disponible",
        "disponibilidad": "Congelador Tensai Tcheu500duof Blanco (170 X 86 Cm)"
      },
      {
        "nombre": "Congelador Ignis Cei250 Horizontal De 252l",
        "precio": "402,99 €",
        "disponibilidad": "Congelador Ignis Cei250 Horizontal De 252l"
      },
      {
        "nombre": "Congelador Ignis Ce1050 102l 860x527x569",
        "precio": "224,99 €",
        "disponibilidad": "Congelador Ignis Ce1050 102l 860x527x569"
      },
      {
        "nombre": "Congelador Horizontal Ignis Ce140 133 Litros",
        "precio": "326,14 €",
        "disponibilidad": "Congelador Horizontal Ignis Ce140 133 Litros"
      },
      {
        "nombre": "Ignis 859991674450 Congelador Horizontal 91.6x140.5x69.8cm Clase E Libre Instalación",
        "precio": "508,86 €",
        "disponibilidad": "Ignis 859991674450 Congelador Horizontal 91.6x140.5x69.8cm Clase E Libre Instalación"
      },
      {
        "nombre": "Arcon Edesa Ezh-0611 Clase A+ 62cm",
        "precio": "220,36 €",
        "disponibilidad": "Arcon Edesa Ezh-0611 Clase A+ 62cm"
      },
      {
        "nombre": "Arcon Congelador Horizontal Edesa Ezh2811",
        "precio": "452,15 €",
        "disponibilidad": "Arcon Congelador Horizontal Edesa Ezh2811"
      }
    ],
    "fuente": "playwright",
    "url": "https://www.carrefour.es/electrodomesticos/frigorificos-congeladores/congeladores/cat4164161/c?offset=216"
  },
  {
    "productos": [
      {
        "nombre": "Infiniton Arcon Congelador Ch-15h85beh, 143 Litros, Función Stand By, E, Blanco",
        "precio": "199 €",
        "disponibilidad": "Infiniton Arcon Congelador Ch-15h85beh, 143 Litros, Función Stand By, E, Blanco"
      },
      {
        "nombre": "Infiniton Arcon Congelador Ch-20h85beh, 198 Litros, Función Stand By, E, Blanco",
        "precio": "239 €",
        "disponibilidad": "Infiniton Arcon Congelador Ch-20h85beh, 198 Litros, Función Stand By, E, Blanco"
      },
      {
        "nombre": "Congelador Vertical Blanco 185cm De 282l | Universalblue",
        "precio": "506,15 €",
        "disponibilidad": "Congelador Vertical Blanco 185cm De 282l | Universalblue"
      },
      {
        "nombre": "Congelador Vertical Inox 185cm De 282l | Universalblue",
        "precio": "526,74 €",
        "disponibilidad": "Congelador Vertical Inox 185cm De 282l | Universalblue"
      },
      {
        "nombre": "Congelador Vertical Chiq 177l | 6 Cajones | Puerta Reversible | Chiq",
        "precio": "339,99 €",
        "disponibilidad": "Congelador Vertical Chiq 177l | 6 Cajones | Puerta Reversible | Chiq"
      },
      {
        "nombre": "Beko Congelador Vertical 70cm 4045l Nofrost, Bpro 700, Blanco - Rfne448e45w",
        "precio": "No disponible",
        "disponibilidad": "Beko Congelador Vertical 70cm 4045l Nofrost, Bpro 700, Blanco - Rfne448e45w"
      },
      {
        "nombre": "Beko Congelador Vertical 54cm 177l Sin Escarcha - Rfnm200e40wn",
        "precio": "No disponible",
        "disponibilidad": "Beko Congelador Vertical 54cm 177l Sin Escarcha - Rfnm200e40wn"
      },
      {
        "nombre": "Beko Congelador Vertical Estático 54cm 196l - Rfsm200t41wn",
        "precio": "No disponible",
        "disponibilidad": "Beko Congelador Vertical Estático 54cm 196l - Rfsm200t41wn"
      }
    ],
    "fuente": "playwright",
    "url": "https://www.carrefour.es/electrodomesticos/frigorificos-congeladores/congeladores/cat4164161/c?offset=240"
  },
  {
    "productos": [
      {
        "nombre": "Congelador Aeg Agb728e3nx",
        "precio": "986,66 €",
        "disponibilidad": "Congelador Aeg Agb728e3nx"
      },
      {
        "nombre": "Congelador Electrolux Lut6ne28w Blanco 1.86m E",
        "precio": "No disponible",
        "disponibilidad": "Congelador Electrolux Lut6ne28w Blanco 1.86m E"
      },
      {
        "nombre": "Congelador Integrable Whirlpool Afb 18401 1.77m",
        "precio": "885,33 €",
        "disponibilidad": "Congelador Integrable Whirlpool Afb 18401 1.77m"
      },
      {
        "nombre": "Congelador Integrable Haier Haun518ew 1.77m E",
        "precio": "745,11 €",
        "disponibilidad": "Congelador Integrable Haier Haun518ew 1.77m E"
      },
      {
        "nombre": "Congelador Teka Rsf 75640 Ss Inox 1.85m",
        "precio": "770,02 €",
        "disponibilidad": "Congelador Teka Rsf 75640 Ss Inox 1.85m"
      },
      {
        "nombre": "Cecotec Frigorífico Bolero Coolmarket Tt 31 Dual White E, Medidas 47,4 X 44,7 X 49,6 Cm.",
        "precio": "136 €",
        "disponibilidad": "Cecotec Frigorífico Bolero Coolmarket Tt 31 Dual White E, Medidas 47,4 X 44,7 X 49,6 Cm."
      },
      {
        "nombre": "Cecotec Mini Frigorífico Grandcooler 20000 L Silentcompress Inox E",
        "precio": "No disponible",
        "disponibilidad": "Cecotec Mini Frigorífico Grandcooler 20000 L Silentcompress Inox E"
      },
      {
        "nombre": "Congelador Arcón Beko Hsm14540 0.76m 205l E",
        "precio": "356,57 €",
        "disponibilidad": "Congelador Arcón Beko Hsm14540 0.76m 205l E"
      },
      {
        "nombre": "Congelador Arcón Beko Hsm29540 1.10m 298l E",
        "precio": "486,40 €",
        "disponibilidad": "Congelador Arcón Beko Hsm29540 1.10m 298l E"
      },
      {
        "nombre": "Congelador Beko Rfne290l41gn Look Inox 1.71m E",
        "precio": "580,78 €",
        "disponibilidad": "Congelador Beko Rfne290l41gn Look Inox 1.71m E"
      },
      {
        "nombre": "Congelador Horizontal Whirlpool F WHS2121",
        "precio": "No disponible",
        "disponibilidad": "Congelador Horizontal Whirlpool F WHS2121"
      },
      {
        "nombre": "Congelador Beko Hsm29540",
        "precio": "686,06 €",
        "disponibilidad": "Congelador Beko Hsm29540"
      },
      {
        "nombre": "Gorenje Fn619eew5 Congelador Vertical Independiente 280 L E Blanco",
        "precio": "No disponible",
        "disponibilidad": "Gorenje Fn619eew5 Congelador Vertical Independiente 280 L E Blanco"
      },
      {
        "nombre": "Gorenje Fn619ees5 Independiente 280 L E Gris",
        "precio": "No disponible",
        "disponibilidad": "Gorenje Fn619ees5 Independiente 280 L E Gris"
      },
      {
        "nombre": "Gorenje Fn619eaxl6 Congelador Congelador Vertical Independiente 280 L E Gris",
        "precio": "No disponible",
        "disponibilidad": "Gorenje Fn619eaxl6 Congelador Congelador Vertical Independiente 280 L E Gris"
      },
      {
        "nombre": "Congelador Vertical Exquisit Nf Clase D Gs230-h-040d Incluido: Incluido: Retirada+instalacion",
        "precio": "360 €",
        "disponibilidad": "Congelador Vertical Exquisit Nf Clase D Gs230-h-040d Incluido: Incluido: Retirada+instalacion"
      },
      {
        "nombre": "Congelador Integrable Liebherr Sifnf 5128 1.79m F",
        "precio": "No disponible",
        "disponibilidad": "Congelador Integrable Liebherr Sifnf 5128 1.79m F"
      },
      {
        "nombre": "Siemens Pantógrafo Congelador Integrado 72l A++ - Gi11vade0",
        "precio": "No disponible",
        "disponibilidad": "Siemens Pantógrafo Congelador Integrado 72l A++ - Gi11vade0"
      },
      {
        "nombre": "Siemens Congelador Vertical 70 Cm No Frost Blanco - Gs58nawcv",
        "precio": "No disponible",
        "disponibilidad": "Siemens Congelador Vertical 70 Cm No Frost Blanco - Gs58nawcv"
      },
      {
        "nombre": "Siemens Iq500 Gu21nade0 Congelador Arcón Congelador Integrado 85 L E Blanco",
        "precio": "790,04 €",
        "disponibilidad": "Siemens Iq500 Gu21nade0 Congelador Arcón Congelador Integrado 85 L E Blanco"
      },
      {
        "nombre": "Bosch Armario Congelador 70cm 365l Nofrost A ++ Blanco - Gsn58awev",
        "precio": "No disponible",
        "disponibilidad": "Bosch Armario Congelador 70cm 365l Nofrost A ++ Blanco - Gsn58awev"
      },
      {
        "nombre": "Bosch Serie 4 Gsn29vwep Congelador Independiente 200 L E Blanco",
        "precio": "No disponible",
        "disponibilidad": "Bosch Serie 4 Gsn29vwep Congelador Independiente 200 L E Blanco"
      },
      {
        "nombre": "Congelador Horizontal 99l Jocel",
        "precio": "No disponible",
        "disponibilidad": "Congelador Horizontal 99l Jocel"
      },
      {
        "nombre": "Congelador Horizontal 198l Jocel",
        "precio": "No disponible",
        "disponibilidad": "Congelador Horizontal 198l Jocel"
      }
    ],
    "fuente": "playwright",
    "url": "https://www.carrefour.es/electrodomesticos/frigorificos-congeladores/congeladores/cat4164161/c?offset=264"
  },
  {
    "productos": [
      {
        "nombre": "Mpm-304-zf-12 Congelador Independiente Inox",
        "precio": "No disponible",
        "disponibilidad": "Mpm-304-zf-12 Congelador Independiente Inox"
      },
      {
        "nombre": "Arcón Congelador Mpm-251-sk-08e/n",
        "precio": "No disponible",
        "disponibilidad": "Arcón Congelador Mpm-251-sk-08e/n"
      },
      {
        "nombre": "Fagor Congelador Arcón 63,5cm 142l - Fcc151me",
        "precio": "No disponible",
        "disponibilidad": "Fagor Congelador Arcón 63,5cm 142l - Fcc151me"
      },
      {
        "nombre": "Congelador Independiente Fz206.5(e) E Blanco",
        "precio": "No disponible",
        "disponibilidad": "Congelador Independiente Fz206.5(e) E Blanco"
      },
      {
        "nombre": "Congelador Amica Fz208.3aa(e)",
        "precio": "No disponible",
        "disponibilidad": "Congelador Amica Fz208.3aa(e)"
      },
      {
        "nombre": "Congelador Haier F HCE103F",
        "precio": "No disponible",
        "disponibilidad": "Congelador Haier F HCE103F"
      },
      {
        "nombre": "Congelador Haier F HCE143F",
        "precio": "No disponible",
        "disponibilidad": "Congelador Haier F HCE143F"
      },
      {
        "nombre": "Hisense Fv245n4aw2 Congelador Vertical Independiente 194 L E Blanco",
        "precio": "No disponible",
        "disponibilidad": "Hisense Fv245n4aw2 Congelador Vertical Independiente 194 L E Blanco"
      },
      {
        "nombre": "Haier Hce321t Arcón Congelador Independiente 319 L D Blanco",
        "precio": "584,76 €",
        "disponibilidad": "Haier Hce321t Arcón Congelador Independiente 319 L D Blanco"
      },
      {
        "nombre": "Haier Hce301e Arcón Congelador Independiente 300 L E Blanco",
        "precio": "No disponible",
        "disponibilidad": "Haier Hce301e Arcón Congelador Independiente 300 L E Blanco"
      },
      {
        "nombre": "Haier Instaswitch H3f330wdh1 Congelador Vertical Independiente 330 L D Blanco",
        "precio": "No disponible",
        "disponibilidad": "Haier Instaswitch H3f330wdh1 Congelador Vertical Independiente 330 L D Blanco"
      },
      {
        "nombre": "Whirlpool Whm22113 3 Arcón Congelador Independiente 219 L D Blanco",
        "precio": "No disponible",
        "disponibilidad": "Whirlpool Whm22113 3 Arcón Congelador Independiente 219 L D Blanco"
      },
      {
        "nombre": "Whirlpool Wh1410 E2 2 Arcón Congelador Independiente 132 L E Blanco",
        "precio": "No disponible",
        "disponibilidad": "Whirlpool Wh1410 E2 2 Arcón Congelador Independiente 132 L E Blanco"
      },
      {
        "nombre": "Whirlpool Wva31612 Nfw 2 Congelador Vertical Independiente 303 L E Blanco",
        "precio": "No disponible",
        "disponibilidad": "Whirlpool Wva31612 Nfw 2 Congelador Vertical Independiente 303 L E Blanco"
      },
      {
        "nombre": "Congelador Vertical Hotpoint Uh8f2cw 263l Blanco",
        "precio": "No disponible",
        "disponibilidad": "Congelador Vertical Hotpoint Uh8f2cw 263l Blanco"
      },
      {
        "nombre": "Indesit Os 2a 200 H2 Arcón Congelador Independiente 204 L E Blanco",
        "precio": "505,35 €",
        "disponibilidad": "Indesit Os 2a 200 H2 Arcón Congelador Independiente 204 L E Blanco"
      },
      {
        "nombre": "Indesit Congelador Vertical Estático 60cm 245l - Ui62wfr",
        "precio": "No disponible",
        "disponibilidad": "Indesit Congelador Vertical Estático 60cm 245l - Ui62wfr"
      },
      {
        "nombre": "Candy Chae 1452e Arcón Congelador Independiente 137 L E Blanco",
        "precio": "No disponible",
        "disponibilidad": "Candy Chae 1452e Arcón Congelador Independiente 137 L E Blanco"
      },
      {
        "nombre": "Candy Cuqs 58ewh Arcón Congelador Independiente 85 L E Blanco",
        "precio": "388,06 €",
        "disponibilidad": "Candy Cuqs 58ewh Arcón Congelador Independiente 85 L E Blanco"
      },
      {
        "nombre": "Congelador Arcón Vitrokitchen Acg191be Gas 1.03cm 191l",
        "precio": "1.149,27 €",
        "disponibilidad": "Congelador Arcón Vitrokitchen Acg191be Gas 1.03cm 191l"
      },
      {
        "nombre": "Infiniton Congelador Vertical Cv-242l70bed, 242 L, 170 Cm, Ciclico, E, Blanco",
        "precio": "No disponible",
        "disponibilidad": "Infiniton Congelador Vertical Cv-242l70bed, 242 L, 170 Cm, Ciclico, E, Blanco"
      },
      {
        "nombre": "Congelador Arcón Svan Sch1501edc 150l E",
        "precio": "189,99 €",
        "disponibilidad": "Congelador Arcón Svan Sch1501edc 150l E"
      },
      {
        "nombre": "Beko Congelador Vertical 60cm 200l Sin Escarcha - B1rfne274w",
        "precio": "No disponible",
        "disponibilidad": "Beko Congelador Vertical 60cm 200l Sin Escarcha - B1rfne274w"
      },
      {
        "nombre": "Lg Congelador Vertical 60cm 324l Plata - Gft61pzcse",
        "precio": "No disponible",
        "disponibilidad": "Lg Congelador Vertical 60cm 324l Plata - Gft61pzcse"
      }
    ],
    "fuente": "playwright",
    "url": "https://www.carrefour.es/electrodomesticos/frigorificos-congeladores/congeladores/cat4164161/c?offset=288"
  },
  {
    "productos": [
      {
        "nombre": "Samsung Brz22700eww Congelador Vertical Independiente 218 L E Blanco",
        "precio": "1.054,34 €",
        "disponibilidad": "Samsung Brz22700eww Congelador Vertical Independiente 218 L E Blanco"
      },
      {
        "nombre": "Samsung Congelador Independiente De Una Puerta 60 Cm 323 L - Rz32c7aeeww",
        "precio": "No disponible",
        "disponibilidad": "Samsung Congelador Independiente De Una Puerta 60 Cm 323 L - Rz32c7aeeww"
      },
      {
        "nombre": "California Arcón Congelador 82cm 199l Blanco - Ccfs199cw-11",
        "precio": "No disponible",
        "disponibilidad": "California Arcón Congelador 82cm 199l Blanco - Ccfs199cw-11"
      },
      {
        "nombre": "California Congelador Arcón 54,5cm 99l Blanco - Ccfs99cw-11",
        "precio": "No disponible",
        "disponibilidad": "California Congelador Arcón 54,5cm 99l Blanco - Ccfs99cw-11"
      },
      {
        "nombre": "Brandt Congelador Vertical Estático 60cm 242l - Bfu7610ew",
        "precio": "No disponible",
        "disponibilidad": "Brandt Congelador Vertical Estático 60cm 242l - Bfu7610ew"
      },
      {
        "nombre": "Congelador Siemens Gi81naef0",
        "precio": "No disponible",
        "disponibilidad": "Congelador Siemens Gi81naef0"
      },
      {
        "nombre": "Congelador Siemens Gs36naidp",
        "precio": "1.320,06 €",
        "disponibilidad": "Congelador Siemens Gs36naidp"
      },
      {
        "nombre": "Siemens Armario Congelador 70cm 365l Nofrost A +++ Blanco - Gs58nawdv",
        "precio": "No disponible",
        "disponibilidad": "Siemens Armario Congelador 70cm 365l Nofrost A +++ Blanco - Gs58nawdv"
      },
      {
        "nombre": "Congelador Siemens Gs36naiep",
        "precio": "1.050,76 €",
        "disponibilidad": "Congelador Siemens Gs36naiep"
      },
      {
        "nombre": "Congelador Siemens Gs36nawep",
        "precio": "No disponible",
        "disponibilidad": "Congelador Siemens Gs36nawep"
      },
      {
        "nombre": "Bosch Congelador Pantógrafo Integrado 97l A ++ - Giv21afe0",
        "precio": "No disponible",
        "disponibilidad": "Bosch Congelador Pantógrafo Integrado 97l A ++ - Giv21afe0"
      },
      {
        "nombre": "Congelador Bosch 186x60 Blanco Gsn36vwfp",
        "precio": "729,95 €",
        "disponibilidad": "Congelador Bosch 186x60 Blanco Gsn36vwfp"
      },
      {
        "nombre": "Bosch Congelador Vertical 70cm 242l Sin Escarcha Blanco - Gsn36vwep",
        "precio": "No disponible",
        "disponibilidad": "Bosch Congelador Vertical 70cm 242l Sin Escarcha Blanco - Gsn36vwep"
      },
      {
        "nombre": "Congelador Balay 3gff563xe",
        "precio": "No disponible",
        "disponibilidad": "Congelador Balay 3gff563xe"
      },
      {
        "nombre": "Sharp Congelador Vertical 65cm 280l Nofrost - Sjsc11cmxwe",
        "precio": "No disponible",
        "disponibilidad": "Sharp Congelador Vertical 65cm 280l Nofrost - Sjsc11cmxwe"
      },
      {
        "nombre": "Congelador Vertical Sharp Sjsc41chxieeu 280l No Frost 41db E Inox 186 Cm",
        "precio": "No disponible",
        "disponibilidad": "Congelador Vertical Sharp Sjsc41chxieeu 280l No Frost 41db E Inox 186 Cm"
      },
      {
        "nombre": "Congelador Vertical Beko F RFNE290L31WN",
        "precio": "No disponible",
        "disponibilidad": "Congelador Vertical Beko F RFNE290L31WN"
      },
      {
        "nombre": "Congelador Vertical Infiniton CV-14C39 - Blanco",
        "precio": "No disponible",
        "disponibilidad": "Congelador Vertical Infiniton CV-14C39 - Blanco"
      },
      {
        "nombre": "Congelador Horizontal 371l Jocel",
        "precio": "No disponible",
        "disponibilidad": "Congelador Horizontal 371l Jocel"
      },
      {
        "nombre": "Congelador Horizontal 287l Jocel",
        "precio": "No disponible",
        "disponibilidad": "Congelador Horizontal 287l Jocel"
      },
      {
        "nombre": "Congelador Vertical Inox 33l Jocel",
        "precio": "No disponible",
        "disponibilidad": "Congelador Vertical Inox 33l Jocel"
      },
      {
        "nombre": "Congelador Horizontal Becken Bcf8336 198l",
        "precio": "305,91 €",
        "disponibilidad": "Congelador Horizontal Becken Bcf8336 198l"
      },
      {
        "nombre": "Fagor Congelador Arcón 165cm 500l - Fcc500e",
        "precio": "No disponible",
        "disponibilidad": "Fagor Congelador Arcón 165cm 500l - Fcc500e"
      },
      {
        "nombre": "Fagor Congelador Arcón Fcc300e - Fcc300e",
        "precio": "No disponible",
        "disponibilidad": "Fagor Congelador Arcón Fcc300e - Fcc300e"
      }
    ],
    "fuente": "playwright",
    "url": "https://www.carrefour.es/electrodomesticos/frigorificos-congeladores/congeladores/cat4164161/c?offset=312"
  },
  {
    "productos": [
      {
        "nombre": "Congelador Horizontal Brandt F BFK101YBW",
        "precio": "255,95 €",
        "disponibilidad": "Congelador Horizontal Brandt F BFK101YBW"
      },
      {
        "nombre": "Congelador Hisense Fv354n4bwe Inox 1.85m E",
        "precio": "653,99 €",
        "disponibilidad": "Congelador Hisense Fv354n4bwe Inox 1.85m E"
      },
      {
        "nombre": "Congelador Horizontal Midea Mdrc280slf01g",
        "precio": "No disponible",
        "disponibilidad": "Congelador Horizontal Midea Mdrc280slf01g"
      },
      {
        "nombre": "Midea Mdrc280fee01 Congelador Horizontal",
        "precio": "284,91 €",
        "disponibilidad": "Midea Mdrc280fee01 Congelador Horizontal"
      },
      {
        "nombre": "Electrolux Congelador Integrado 98 L A ++ - Lub3ae88s",
        "precio": "No disponible",
        "disponibilidad": "Electrolux Congelador Integrado 98 L A ++ - Lub3ae88s"
      },
      {
        "nombre": "Electrolux Congelador Arcón 54.5cm 98l A + Blanco - Lcb1af10w0",
        "precio": "No disponible",
        "disponibilidad": "Electrolux Congelador Arcón 54.5cm 98l A + Blanco - Lcb1af10w0"
      },
      {
        "nombre": "Congelador Zanussi Zuan28fx",
        "precio": "794,72 €",
        "disponibilidad": "Congelador Zanussi Zuan28fx"
      },
      {
        "nombre": "Whirlpool Congelador Arcón 140cm 390l A ++ Blanco - Whm39112",
        "precio": "No disponible",
        "disponibilidad": "Whirlpool Congelador Arcón 140cm 390l A ++ Blanco - Whm39112"
      }
    ],
    "fuente": "playwright",
    "url": "https://www.carrefour.es/electrodomesticos/frigorificos-congeladores/congeladores/cat4164161/c?offset=336"
  },
  {
    "productos": [
      {
        "nombre": "Congelador Vertical Samsung Rz32c76bes9/ef",
        "precio": "1062 €",
        "disponibilidad": "Congelador Vertical Samsung Rz32c76bes9/ef"
      },
      {
        "nombre": "Congelador Vertical Samsung Rz32c76ce41/ef",
        "precio": "No disponible",
        "disponibilidad": "Congelador Vertical Samsung Rz32c76ce41/ef"
      },
      {
        "nombre": "Congelador Vertical Samsung Rz32c7adeww/ef",
        "precio": "922,63 €",
        "disponibilidad": "Congelador Vertical Samsung Rz32c7adeww/ef"
      },
      {
        "nombre": "Arcon Liebherr Ft3300 Bco 1.04m Conservador",
        "precio": "1.216,76 €",
        "disponibilidad": "Arcon Liebherr Ft3300 Bco 1.04m Conservador"
      },
      {
        "nombre": "Congelador Aeg Oab6i82ef Blanco 95 L",
        "precio": "825,07 €",
        "disponibilidad": "Congelador Aeg Oab6i82ef Blanco 95 L"
      },
      {
        "nombre": "Congelador Hisense Ft3b213sawe Blanco 235 L",
        "precio": "1.183,61 €",
        "disponibilidad": "Congelador Hisense Ft3b213sawe Blanco 235 L"
      },
      {
        "nombre": "Gorenje F492pw Congelador Congelador Vertical Independiente 82 L F Blanco",
        "precio": "No disponible",
        "disponibilidad": "Gorenje F492pw Congelador Congelador Vertical Independiente 82 L F Blanco"
      },
      {
        "nombre": "Gorenje F4142pw Congelador Vertical Independiente 165 L E Blanco",
        "precio": "No disponible",
        "disponibilidad": "Gorenje F4142pw Congelador Vertical Independiente 165 L E Blanco"
      }
    ],
    "fuente": "playwright",
    "url": "https://www.carrefour.es/electrodomesticos/frigorificos-congeladores/congeladores/cat4164161/c?offset=360"
  },
  {
    "productos": [
      {
        "nombre": "Congelador Teka Tgf3 270 Nf Ss Eu Inox 1.71m",
        "precio": "772,50 €",
        "disponibilidad": "Congelador Teka Tgf3 270 Nf Ss Eu Inox 1.71m"
      },
      {
        "nombre": "Cecotec Congelador Horizontal Bolero Coolmarket Chest 99 Black E",
        "precio": "199 €",
        "disponibilidad": "Cecotec Congelador Horizontal Bolero Coolmarket Chest 99 Black E"
      },
      {
        "nombre": "Congelador Arcón Svan Svch101fs Cíclico 85 Litros",
        "precio": "288,99 €",
        "disponibilidad": "Congelador Arcón Svan Svch101fs Cíclico 85 Litros"
      },
      {
        "nombre": "Congelador Beko B3rmfne314xb Acero 185 X 60 Cm",
        "precio": "826,13 €",
        "disponibilidad": "Congelador Beko B3rmfne314xb Acero 185 X 60 Cm"
      },
      {
        "nombre": "Congelador Candy Chae1002e",
        "precio": "338,79 €",
        "disponibilidad": "Congelador Candy Chae1002e"
      },
      {
        "nombre": "Gorenje Fh10eaw Congelador Arcón Congelador Independiente 95 L E Blanco",
        "precio": "No disponible",
        "disponibilidad": "Gorenje Fh10eaw Congelador Arcón Congelador Independiente 95 L E Blanco"
      },
      {
        "nombre": "Congelador Horizontal Gorenje Fh14eaw",
        "precio": "No disponible",
        "disponibilidad": "Congelador Horizontal Gorenje Fh14eaw"
      },
      {
        "nombre": "Cómoda Vertical Siemens Gi81nace0 212l Blanco",
        "precio": "1.145,56 €",
        "disponibilidad": "Cómoda Vertical Siemens Gi81nace0 212l Blanco"
      }
    ],
    "fuente": "playwright",
    "url": "https://www.carrefour.es/electrodomesticos/frigorificos-congeladores/congeladores/cat4164161/c?offset=384"
  },
  {
    "productos": [
      {
        "nombre": "Mpm 46-zs-01b Congelador Independiente 34 L Blanco",
        "precio": "No disponible",
        "disponibilidad": "Mpm 46-zs-01b Congelador Independiente 34 L Blanco"
      },
      {
        "nombre": "Dometic Acx3 40 Nevera De Absorción Portátil, 41 L, 28-30/37 Mbar",
        "precio": "No disponible",
        "disponibilidad": "Dometic Acx3 40 Nevera De Absorción Portátil, 41 L, 28-30/37 Mbar"
      },
      {
        "nombre": "Aeg Abe818e6ns Congelador Vertical Integrable Serie 7000 No Frost De 1 77 M X 54 8 Cm Display Digital 5 Cajones Y 2 Puertas Abat",
        "precio": "1.307,96 €",
        "disponibilidad": "Aeg Abe818e6ns Congelador Vertical Integrable Serie 7000 No Frost De 1 77 M X 54 8 Cm Display Digital 5 Cajones Y 2 Puertas Abat"
      },
      {
        "nombre": "Ignis Ce210 Eg 2 Congelador Horizontal 86.5x80.6x64.2cm Clase E Libre Instalación",
        "precio": "No disponible",
        "disponibilidad": "Ignis Ce210 Eg 2 Congelador Horizontal 86.5x80.6x64.2cm Clase E Libre Instalación"
      },
      {
        "nombre": "Ignis Cei250 2 Congelador Horizontal 91.6x101x369.8cm Clase E Libre Instalación",
        "precio": "418,94 €",
        "disponibilidad": "Ignis Cei250 2 Congelador Horizontal 91.6x101x369.8cm Clase E Libre Instalación"
      },
      {
        "nombre": "Ignis Co310eg2 Congelador Horizontal 91.6x118x69.8cm Clase E Libre Instalación",
        "precio": "436,34 €",
        "disponibilidad": "Ignis Co310eg2 Congelador Horizontal 91.6x118x69.8cm Clase E Libre Instalación"
      },
      {
        "nombre": "Arca Vertical Indesit Ui6f2tw Blanca",
        "precio": "510,88 €",
        "disponibilidad": "Arca Vertical Indesit Ui6f2tw Blanca"
      },
      {
        "nombre": "Indesit Ui6 F2t S Congelador Vertical De 167x59.5x64.5cm Clase E Libre Instalacion",
        "precio": "534,90 €",
        "disponibilidad": "Indesit Ui6 F2t S Congelador Vertical De 167x59.5x64.5cm Clase E Libre Instalacion"
      },
      {
        "nombre": "Congelador Vertical Indesit Ui-6-2-w",
        "precio": "No disponible",
        "disponibilidad": "Congelador Vertical Indesit Ui-6-2-w"
      },
      {
        "nombre": "Congelador Vertical Candy Cuqs-58-ew",
        "precio": "No disponible",
        "disponibilidad": "Congelador Vertical Candy Cuqs-58-ew"
      },
      {
        "nombre": "Edesa Ezs-0813 Wh /a Congelador Tablatop De 84.5x55.3x57.4cm Clase E",
        "precio": "219,84 €",
        "disponibilidad": "Edesa Ezs-0813 Wh /a Congelador Tablatop De 84.5x55.3x57.4cm Clase E"
      },
      {
        "nombre": "Edesa Ezh-2011 /c Congelador Horizontal 85x77x56cm Clase E Libre Instalacion",
        "precio": "No disponible",
        "disponibilidad": "Edesa Ezh-2011 /c Congelador Horizontal 85x77x56cm Clase E Libre Instalacion"
      },
      {
        "nombre": "Rommer Cve 121 Frigorífico Independiente 145 L E Blanco",
        "precio": "358,23 €",
        "disponibilidad": "Rommer Cve 121 Frigorífico Independiente 145 L E Blanco"
      },
      {
        "nombre": "Cecotec Nevera Pequeña De 25 L, Bolero Minicooling Bahamas Black, 12v-220v, Compatible Con Coches Y Caravanas, 7 A 65°c, Función Enfriamiento Y Calentamiento, Transporte Fácil",
        "precio": "No disponible",
        "disponibilidad": "Cecotec Nevera Pequeña De 25 L, Bolero Minicooling Bahamas Black, 12v-220v, Compatible Con Coches Y Caravanas, 7 A 65°c, Función Enfriamiento Y Calentamiento, Transporte Fácil"
      },
      {
        "nombre": "Arcon Schneider Sche 100s Clase A+ 100l",
        "precio": "261,21 €",
        "disponibilidad": "Arcon Schneider Sche 100s Clase A+ 100l"
      },
      {
        "nombre": "Muvip Nevera Portatil De Compresor 30l - Proteccion Bateria Vehiculo - Temperatura -20º/+20º - Conexion 12/24/220v - Compresor Silencioso - Control Bluetooth - Color Gris",
        "precio": "247,99 €",
        "disponibilidad": "Muvip Nevera Portatil De Compresor 30l - Proteccion Bateria Vehiculo - Temperatura -20º/+20º - Conexion 12/24/220v - Compresor Silencioso - Control Bluetooth - Color Gris"
      },
      {
        "nombre": "Muvip Nevera De Compresor Portatil 20 Litros 50w - Asas De Transporte - Compresor Silencioso - Color Negro",
        "precio": "244,94 €",
        "disponibilidad": "Muvip Nevera De Compresor Portatil 20 Litros 50w - Asas De Transporte - Compresor Silencioso - Color Negro"
      },
      {
        "nombre": "Congelador Vertical Infiniton Cv-870ix- Inox, 380 Litros, Inverter, No Frost, Display, A++",
        "precio": "No disponible",
        "disponibilidad": "Congelador Vertical Infiniton Cv-870ix- Inox, 380 Litros, Inverter, No Frost, Display, A++"
      },
      {
        "nombre": "Congelador Arcón Corberó Cch 208 W Clase A+",
        "precio": "325,25 €",
        "disponibilidad": "Congelador Arcón Corberó Cch 208 W Clase A+"
      },
      {
        "nombre": "Solthermic Congelador Chs395 1,31 395l Dual Technology",
        "precio": "No disponible",
        "disponibilidad": "Solthermic Congelador Chs395 1,31 395l Dual Technology"
      },
      {
        "nombre": "Infiniton Ch-40h86weh Congelador Arcón Congelador Independiente 400 L E Blanco",
        "precio": "499 €",
        "disponibilidad": "Infiniton Ch-40h86weh Congelador Arcón Congelador Independiente 400 L E Blanco"
      },
      {
        "nombre": "Arca Vertical Lg Gfe41pzgsz 324l Gris",
        "precio": "No disponible",
        "disponibilidad": "Arca Vertical Lg Gfe41pzgsz 324l Gris"
      },
      {
        "nombre": "Samsung Smart Rz32c7bees9/ef - Congelador Vertical Nofrost E Alto 186 Cm 323 Litros Inox",
        "precio": "No disponible",
        "disponibilidad": "Samsung Smart Rz32c7bees9/ef - Congelador Vertical Nofrost E Alto 186 Cm 323 Litros Inox"
      },
      {
        "nombre": "Samsung Rz32c7cdewwef Congelador No Frost 186x60 E Twin",
        "precio": "952,75 €",
        "disponibilidad": "Samsung Rz32c7cdewwef Congelador No Frost 186x60 E Twin"
      }
    ],
    "fuente": "playwright",
    "url": "https://www.carrefour.es/electrodomesticos/frigorificos-congeladores/congeladores/cat4164161/c?offset=408"
  },
  {
    "productos": [
      {
        "nombre": "Frigorífico Americano Lg Gsxe81pybd Acero",
        "precio": "No disponible",
        "disponibilidad": "Frigorífico Americano Lg Gsxe81pybd Acero"
      },
      {
        "nombre": "Arcon Liebherr Gt2632 Bco 0.92m",
        "precio": "773,54 €",
        "disponibilidad": "Arcon Liebherr Gt2632 Bco 0.92m"
      },
      {
        "nombre": "Congelador Liebherr Gg-5210 Con 14 Cestas",
        "precio": "2.283,54 €",
        "disponibilidad": "Congelador Liebherr Gg-5210 Con 14 Cestas"
      },
      {
        "nombre": "Congelador Liebherr Gg-5210 Con 14 Cajones",
        "precio": "2.276,80 €",
        "disponibilidad": "Congelador Liebherr Gg-5210 Con 14 Cajones"
      },
      {
        "nombre": "Bosch Serie 6 Gsn54awdv Congelador Congelador Vertical Independiente 328 L D Blanco",
        "precio": "No disponible",
        "disponibilidad": "Bosch Serie 6 Gsn54awdv Congelador Congelador Vertical Independiente 328 L D Blanco"
      },
      {
        "nombre": "Haier Hce200e Arcón Congelador Independiente 196 L E Blanco",
        "precio": "280,33 €",
        "disponibilidad": "Haier Hce200e Arcón Congelador Independiente 196 L E Blanco"
      },
      {
        "nombre": "Congelador Horizontal Frigelux CCO147BE, 85 cm, 147 L, Eficiencia E - Blanco",
        "precio": "No disponible",
        "disponibilidad": "Congelador Horizontal Frigelux CCO147BE, 85 cm, 147 L, Eficiencia E - Blanco"
      },
      {
        "nombre": "Congelador Vertical Frigelux E CV40",
        "precio": "No disponible",
        "disponibilidad": "Congelador Vertical Frigelux E CV40"
      }
    ],
    "fuente": "playwright",
    "url": "https://www.carrefour.es/electrodomesticos/frigorificos-congeladores/congeladores/cat4164161/c?offset=432"
  }
]